pg
setup.py
modules/__init__.py
modules/pgen.py
passgify.egg-info/PKG-INFO
passgify.egg-info/SOURCES.txt
passgify.egg-info/dependency_links.txt
passgify.egg-info/requires.txt
passgify.egg-info/top_level.txt