Metadata-Version: 1.0
Name: passgify
Version: 0.2.3
Summary: A tool to deterministically generate pseudo-random passwords
Home-page: https://github.com/bfrizb/passgify
Author: Brian Frisbie
Author-email: bfrizb@github.com
License: UNKNOWN
Platform: UNKNOWN
